aiohttp_csrf/__init__.py
aiohttp_csrf/policy.py
aiohttp_csrf/storage.py
aiohttp_csrf/token_generator.py
aiohttp_csrf-0.1.1.dist-info/WHEEL
aiohttp_csrf-0.1.1.dist-info/METADATA
aiohttp_csrf-0.1.1.dist-info/RECORD
