Metadata-Version: 2.1
Name: aiohttp-csrf
Version: 0.1.1
Summary: CSRF protection for aiohttp-server
Home-page: https://github.com/TensorTom/aiohttp-csrf
License: MIT
Author: TensorTom
Requires-Python: >=3.8.3,<4
Classifier: License :: OSI Approved :: MIT License
Classifier: Programming Language :: Python :: 3
Requires-Dist: aiohttp (>=3.6.2,<4.1)
Requires-Dist: aiohttp-session (>=2,<3)
Requires-Dist: blake3 (>=0.1.8,<0.2.0)
